modelbucket/__init__.py
modelbucket/modelbucket.py
model_bucket-1.0.1.dist-info/METADATA
model_bucket-1.0.1.dist-info/WHEEL
model_bucket-1.0.1.dist-info/top_level.txt
model_bucket-1.0.1.dist-info/RECORD
