Metadata-Version: 2.1
Name: model-bucket
Version: 1.0.1
Summary: ModelBucket deployment package
Author: Adi_K527
Author-email: <adikandakurtikar2@gmail.com>
Keywords: python,ML,Deployment
Classifier: Development Status :: 1 - Planning
Classifier: Intended Audience :: Developers
Classifier: Programming Language :: Python :: 3
Classifier: Operating System :: Unix
Classifier: Operating System :: MacOS :: MacOS X
Classifier: Operating System :: Microsoft :: Windows
Requires-Dist: requests
